{"timestamp": 1695440464204, "configuration": {"server": "http://127.0.0.1:8000/api/recommender/", "query_search": 544, "individual_size": 10, "population_size": 50, "p_crossover": 0.594626648777422, "p_mutation": 0.2839692912126437, "max_generations": 30, "size_hall_of_fame": 3, "seed": 42}, "statisticsData": [{"gen": 0, "nevals": 50, "avg": 0.51, "std": 0.06999999999999999, "min": 0.5, "max": 1.0}, {"gen": 1, "nevals": 36, "avg": 0.56, "std": 0.16248076809271922, "min": 0.5, "max": 1.0}, {"gen": 2, "nevals": 38, "avg": 0.68, "std": 0.24, "min": 0.5, "max": 1.0}, {"gen": 3, "nevals": 29, "avg": 0.88, "std": 0.21354156504062624, "min": 0.5, "max": 1.0}, {"gen": 4, "nevals": 36, "avg": 0.98, "std": 0.09797958971132714, "min": 0.5, "max": 1.0}, {"gen": 5, "nevals": 37, "avg": 0.96, "std": 0.13564659966250536, "min": 0.5, "max": 1.0}, {"gen": 6, "nevals": 38, "avg": 1.0, "std": 0.0, "min": 1.0, "max": 1.0}, {"gen": 7, "nevals": 42, "avg": 1.0, "std": 0.0, "min": 1.0, "max": 1.0}, {"gen": 8, "nevals": 35, "avg": 0.99, "std": 0.06999999999999999, "min": 0.5, "max": 1.0}, {"gen": 9, "nevals": 36, "avg": 0.98, "std": 0.09797958971132714, "min": 0.5, "max": 1.0}, {"gen": 10, "nevals": 34, "avg": 1.0, "std": 0.0, "min": 1.0, "max": 1.0}, {"gen": 11, "nevals": 40, "avg": 0.98, "std": 0.09797958971132714, "min": 0.5, "max": 1.0}, {"gen": 12, "nevals": 40, "avg": 0.95, "std": 0.15, "min": 0.5, "max": 1.0}, {"gen": 13, "nevals": 37, "avg": 0.99, "std": 0.06999999999999999, "min": 0.5, "max": 1.0}, {"gen": 14, "nevals": 47, "avg": 0.95, "std": 0.15, "min": 0.5, "max": 1.0}, {"gen": 15, "nevals": 41, "avg": 0.98, "std": 0.09797958971132714, "min": 0.5, "max": 1.0}, {"gen": 16, "nevals": 35, "avg": 1.0, "std": 0.0, "min": 1.0, "max": 1.0}, {"gen": 17, "nevals": 29, "avg": 1.0, "std": 0.0, "min": 1.0, "max": 1.0}, {"gen": 18, "nevals": 33, "avg": 1.0, "std": 0.0, "min": 1.0, "max": 1.0}, {"gen": 19, "nevals": 30, "avg": 1.0, "std": 0.0, "min": 1.0, "max": 1.0}, {"gen": 20, "nevals": 40, "avg": 0.95, "std": 0.15, "min": 0.5, "max": 1.0}, {"gen": 21, "nevals": 29, "avg": 1.0, "std": 0.0, "min": 1.0, "max": 1.0}, {"gen": 22, "nevals": 30, "avg": 1.0, "std": 0.0, "min": 1.0, "max": 1.0}, {"gen": 23, "nevals": 35, "avg": 1.0, "std": 0.0, "min": 1.0, "max": 1.0}, {"gen": 24, "nevals": 43, "avg": 1.0, "std": 0.0, "min": 1.0, "max": 1.0}, {"gen": 25, "nevals": 35, "avg": 0.97, "std": 0.11874342087037919, "min": 0.5, "max": 1.0}, {"gen": 26, "nevals": 41, "avg": 0.98, "std": 0.09797958971132714, "min": 0.5, "max": 1.0}, {"gen": 27, "nevals": 39, "avg": 1.0, "std": 0.0, "min": 1.0, "max": 1.0}, {"gen": 28, "nevals": 33, "avg": 0.99, "std": 0.06999999999999999, "min": 0.5, "max": 1.0}, {"gen": 29, "nevals": 40, "avg": 0.99, "std": 0.06999999999999999, "min": 0.5, "max": 1.0}, {"gen": 30, "nevals": 34, "avg": 0.98, "std": 0.09797958971132714, "min": 0.5, "max": 1.0}], "recommendedMovies": [{"movieId": 839, "title": "Crow: City of Angels, The", "year": 1996, "genres": "Action|Thriller", "url_poster": "https://m.media-amazon.com/images/M/MV5BMmY0NWRhOGQtZGNlYi00YmNlLTlmZmMtMzFhY2Y0OGFmYzM3XkEyXkFqcGdeQXVyNjMwMjk0MTQ@._V1_SY150_CR1,0,101,150_.jpg", "imdbId": "0115986"}, {"movieId": 1826, "title": "Barney's Great Adventure", "year": 1998, "genres": "Adventure|Children", "url_poster": "https://m.media-amazon.com/images/M/MV5BOGQwZDFjMGEtMjE0Yi00MjE4LTllNDMtYWFkYzVjM2JmZGJkXkEyXkFqcGdeQXVyNjMwMjk0MTQ@._V1_SX101_CR0,0,101,150_.jpg", "imdbId": "0120598"}, {"movieId": 2051, "title": "Herbie Goes to Monte Carlo", "year": 1977, "genres": "Adventure|Children|Comedy", "url_poster": "https://m.media-amazon.com/images/M/MV5BOTllNTk2YWItYmQ5Yy00MGUzLTgxMzAtMjNmOTU1ODgxOGI4L2ltYWdlL2ltYWdlXkEyXkFqcGdeQXVyNzc5MjA3OA@@._V1_SX101_CR0,0,101,150_.jpg", "imdbId": "0076137"}, {"movieId": 2123, "title": "All Dogs Go to Heaven", "year": 1989, "genres": "Animation|Children|Comedy|Drama|Fantasy", "url_poster": "https://m.media-amazon.com/images/M/MV5BMTI4ZWRmNTAtOWIyZC00Njk0LWIzZGItYjE0NDVlM2Q4ZWJjXkEyXkFqcGdeQXVyNTUyMzE4Mzg@._V1_SX101_CR0,0,101,150_.jpg", "imdbId": "0096787"}, {"movieId": 4533, "title": "Return of the Living Dead, The", "year": 1985, "genres": "Comedy|Horror|Sci-Fi", "url_poster": "https://m.media-amazon.com/images/M/MV5BNmNlM2RmZTEtNGVhNS00MjU3LWI1OWUtMWI5MThlYTVjM2M5XkEyXkFqcGdeQXVyMTUzMDUzNTI3._V1_SX101_CR0,0,101,150_.jpg", "imdbId": "0089907"}, {"movieId": 6237, "title": "Glenn Miller Story, The", "year": 1953, "genres": "Drama", "url_poster": "https://m.media-amazon.com/images/M/MV5BMzc1NGQ1NzQtY2I2ZS00NzE4LWI4ZDQtNWRiNmIyMzUwZmFmXkEyXkFqcGdeQXVyMjI4MjA5MzA@._V1_SX101_CR0,0,101,150_.jpg", "imdbId": "0047030"}, {"movieId": 45730, "title": "Lady in the Water", "year": 2006, "genres": "Drama|Fantasy|Mystery", "url_poster": "https://m.media-amazon.com/images/M/MV5BMjEyNTc0NTk5M15BMl5BanBnXkFtZTcwMDE5NzkyMw@@._V1_SY150_CR0,0,101,150_.jpg", "imdbId": "0452637"}, {"movieId": 62511, "title": "Synecdoche, New York", "year": 2008, "genres": "Comedy|Drama", "url_poster": "https://m.media-amazon.com/images/M/MV5BMjA0MjIyOTI3MF5BMl5BanBnXkFtZTcwODM5NTY5MQ@@._V1_SY150_CR0,0,101,150_.jpg", "imdbId": "0383028"}, {"movieId": 173535, "title": "The Adventures of Sherlock Holmes and Doctor Watson: The Hunt for the Tiger", "year": 1980, "genres": "(no genres listed)", "url_poster": "https://m.media-amazon.com/images/M/MV5BOWMwMTBjOTYtMzI1YS00ZGMyLTkxZmItZWZlMmVjZThjYmRjXkEyXkFqcGdeQXVyNTE1MDE2MzY@._V1_SY150_CR83,0,101,150_.jpg", "imdbId": "0459945"}, {"movieId": 193587, "title": "Bungo Stray Dogs: Dead Apple", "year": 2018, "genres": "Action|Animation", "url_poster": "", "imdbId": "8391976"}]}